<?xml version="1.0" encoding="utf-8" ?>
<c2layout>
    <name>Kuis Pecahan No5 Lv2</name>
    <sid>604993546950625</sid>
    <event-sheet>Kuis Pecahan No 5 Lv2</event-sheet>
    <size>
        <width>1280</width>
        <height>720</height>
    </size>
    <margins>
        <horizontal>500</horizontal>
        <vertical>500</vertical>
    </margins>
    <unbounded-scrolling>0</unbounded-scrolling>
    <layers>
        <layer name="Layer 0" sid="624975575853041">
            <initially-visible>1</initially-visible>
            <background-color>255,255,255</background-color>
            <transparent>0</transparent>
            <parallax>
                <x>1</x>
                <y>1</y>
            </parallax>
            <zoom-rate>1</zoom-rate>
            <opacity>1</opacity>
            <force-own-texture>0</force-own-texture>
            <global>0</global>
            <use-render-cells>0</use-render-cells>
            <blend-mode>0</blend-mode>
            <effect-fallback>0</effect-fallback>
            <instances>
                <instance type="bgLv2Bilangan" uid="1712">
                    <properties>
                        <initial-visibility>Visible</initial-visibility>
                        <initial-animation>Default</initial-animation>
                        <initial-frame>0</initial-frame>
                        <collisions>Enabled</collisions>
                    </properties>
                    <blend-mode>0</blend-mode>
                    <effect-fallback>0</effect-fallback>
                    <world>
                        <x>657</x>
                        <y>380</y>
                        <z>0</z>
                        <width>1324</width>
                        <height>767</height>
                        <depth>0</depth>
                        <hotspotX>0.5</hotspotX>
                        <hotspotY>0.5</hotspotY>
                        <angle>0</angle>
                        <opacity>1</opacity>
                    </world>
                </instance>
                <instance type="layoutJawabanLv2Bilangan" uid="1713">
                    <properties>
                        <initial-visibility>Visible</initial-visibility>
                        <initial-animation>Default</initial-animation>
                        <initial-frame>0</initial-frame>
                        <collisions>Enabled</collisions>
                    </properties>
                    <blend-mode>0</blend-mode>
                    <effect-fallback>0</effect-fallback>
                    <world>
                        <x>1047</x>
                        <y>239</y>
                        <z>0</z>
                        <width>448.660614014</width>
                        <height>98.486473083</height>
                        <depth>0</depth>
                        <hotspotX>0.500717342</hotspotX>
                        <hotspotY>0.503268003</hotspotY>
                        <angle>0</angle>
                        <opacity>1</opacity>
                    </world>
                </instance>
                <instance type="text_jawaban" uid="1714">
                    <properties>
                        <text>1/2</text>
                        <initial-visibility>Visible</initial-visibility>
                        <font>BM HANNA,-34.6667,400,0</font>
                        <color>255,255,255</color>
                        <horizontal-alignment>Center</horizontal-alignment>
                        <vertical-alignment>Center</vertical-alignment>
                        <hotspot>Top</hotspot>
                        <wrapping>Word</wrapping>
                        <line-height>0</line-height>
                    </properties>
                    <blend-mode>0</blend-mode>
                    <effect-fallback>0</effect-fallback>
                    <world>
                        <x>1041</x>
                        <y>201</y>
                        <z>0</z>
                        <width>364</width>
                        <height>81</height>
                        <depth>0</depth>
                        <hotspotX>0.5</hotspotX>
                        <hotspotY>0</hotspotY>
                        <angle>0</angle>
                        <opacity>1</opacity>
                    </world>
                </instance>
                <instance type="tandaSalah" uid="1715">
                    <properties>
                        <initial-visibility>Visible</initial-visibility>
                        <initial-animation>Default</initial-animation>
                        <initial-frame>0</initial-frame>
                        <collisions>Enabled</collisions>
                    </properties>
                    <behavior-instances>
                        <behavior-instance type="LiteTween">
                            <properties>
                                <active-on-start>No</active-on-start>
                                <tweened-property>Position</tweened-property>
                                <function>EaseInQuad</function>
                                <target>654, 259</target>
                                <target-mode>Absolute</target-mode>
                                <duration>1.5</duration>
                                <enforce-mode>Enforce</enforce-mode>
                            </properties>
                        </behavior-instance>
                    </behavior-instances>
                    <blend-mode>0</blend-mode>
                    <effect-fallback>0</effect-fallback>
                    <world>
                        <x>647</x>
                        <y>1044</y>
                        <z>0</z>
                        <width>479.468444824</width>
                        <height>479.468444824</height>
                        <depth>0</depth>
                        <hotspotX>0.5</hotspotX>
                        <hotspotY>0.5</hotspotY>
                        <angle>0</angle>
                        <opacity>1</opacity>
                    </world>
                </instance>
                <instance type="btnHome" uid="1716">
                    <properties>
                        <initial-visibility>Visible</initial-visibility>
                        <initial-animation>Default</initial-animation>
                        <initial-frame>0</initial-frame>
                        <collisions>Enabled</collisions>
                    </properties>
                    <behavior-instances>
                        <behavior-instance type="LiteTween">
                            <properties>
                                <active-on-start>No</active-on-start>
                                <tweened-property>Position</tweened-property>
                                <function>EaseInQuad</function>
                                <target>452, 660</target>
                                <target-mode>Absolute</target-mode>
                                <duration>1.5</duration>
                                <enforce-mode>Enforce</enforce-mode>
                            </properties>
                        </behavior-instance>
                    </behavior-instances>
                    <blend-mode>0</blend-mode>
                    <effect-fallback>0</effect-fallback>
                    <world>
                        <x>445</x>
                        <y>1439</y>
                        <z>0</z>
                        <width>75.330001831</width>
                        <height>63.14899826</height>
                        <depth>0</depth>
                        <hotspotX>0.5</hotspotX>
                        <hotspotY>0.5</hotspotY>
                        <angle>0</angle>
                        <opacity>1</opacity>
                    </world>
                </instance>
                <instance type="btnKeSoal" uid="1717">
                    <properties>
                        <initial-visibility>Visible</initial-visibility>
                        <initial-animation>Default</initial-animation>
                        <initial-frame>0</initial-frame>
                        <collisions>Enabled</collisions>
                    </properties>
                    <behavior-instances>
                        <behavior-instance type="LiteTween">
                            <properties>
                                <active-on-start>No</active-on-start>
                                <tweened-property>Position</tweened-property>
                                <function>EaseInQuad</function>
                                <target>747, 668</target>
                                <target-mode>Absolute</target-mode>
                                <duration>1.5</duration>
                                <enforce-mode>Enforce</enforce-mode>
                            </properties>
                        </behavior-instance>
                    </behavior-instances>
                    <blend-mode>0</blend-mode>
                    <effect-fallback>0</effect-fallback>
                    <world>
                        <x>740</x>
                        <y>1444</y>
                        <z>0</z>
                        <width>422.596832275</width>
                        <height>89.645721436</height>
                        <depth>0</depth>
                        <hotspotX>0.500077367</hotspotX>
                        <hotspotY>0.500364721</hotspotY>
                        <angle>0</angle>
                        <opacity>1</opacity>
                    </world>
                </instance>
                <instance type="jawabKuSalah" uid="1718">
                    <properties>
                        <text>Jawaban Salah</text>
                        <initial-visibility>Visible</initial-visibility>
                        <font>Arial Rounded MT Bold,-64,400,0</font>
                        <color>255,0,0</color>
                        <horizontal-alignment>Center</horizontal-alignment>
                        <vertical-alignment>Center</vertical-alignment>
                        <hotspot>Top-left</hotspot>
                        <wrapping>Word</wrapping>
                        <line-height>0</line-height>
                    </properties>
                    <behavior-instances>
                        <behavior-instance type="LiteTween">
                            <properties>
                                <active-on-start>No</active-on-start>
                                <tweened-property>Position</tweened-property>
                                <function>EaseInQuad</function>
                                <target>371, 519</target>
                                <target-mode>Absolute</target-mode>
                                <duration>1.5</duration>
                                <enforce-mode>Enforce</enforce-mode>
                            </properties>
                        </behavior-instance>
                    </behavior-instances>
                    <blend-mode>0</blend-mode>
                    <effect-fallback>0</effect-fallback>
                    <world>
                        <x>364</x>
                        <y>1288</y>
                        <z>0</z>
                        <width>568</width>
                        <height>85</height>
                        <depth>0</depth>
                        <hotspotX>0</hotspotX>
                        <hotspotY>0</hotspotY>
                        <angle>0</angle>
                        <opacity>1</opacity>
                    </world>
                </instance>
                <instance type="layoutJawabanLv2Bilangan" uid="1719">
                    <properties>
                        <initial-visibility>Visible</initial-visibility>
                        <initial-animation>Default</initial-animation>
                        <initial-frame>0</initial-frame>
                        <collisions>Enabled</collisions>
                    </properties>
                    <blend-mode>0</blend-mode>
                    <effect-fallback>0</effect-fallback>
                    <world>
                        <x>1047</x>
                        <y>378</y>
                        <z>0</z>
                        <width>448.660614014</width>
                        <height>98.486473083</height>
                        <depth>0</depth>
                        <hotspotX>0.500717342</hotspotX>
                        <hotspotY>0.503268003</hotspotY>
                        <angle>0</angle>
                        <opacity>1</opacity>
                    </world>
                </instance>
                <instance type="text_jawaban" uid="1720">
                    <properties>
                        <text>4/6</text>
                        <initial-visibility>Visible</initial-visibility>
                        <font>BM HANNA,-34.6667,400,0</font>
                        <color>255,255,255</color>
                        <horizontal-alignment>Center</horizontal-alignment>
                        <vertical-alignment>Center</vertical-alignment>
                        <hotspot>Top</hotspot>
                        <wrapping>Word</wrapping>
                        <line-height>0</line-height>
                    </properties>
                    <blend-mode>0</blend-mode>
                    <effect-fallback>0</effect-fallback>
                    <world>
                        <x>1041</x>
                        <y>340</y>
                        <z>0</z>
                        <width>364</width>
                        <height>81</height>
                        <depth>0</depth>
                        <hotspotX>0.5</hotspotX>
                        <hotspotY>0</hotspotY>
                        <angle>0</angle>
                        <opacity>1</opacity>
                    </world>
                </instance>
                <instance type="layoutJawabanLv2Bilangan" uid="1721">
                    <properties>
                        <initial-visibility>Visible</initial-visibility>
                        <initial-animation>Default</initial-animation>
                        <initial-frame>0</initial-frame>
                        <collisions>Enabled</collisions>
                    </properties>
                    <blend-mode>0</blend-mode>
                    <effect-fallback>0</effect-fallback>
                    <world>
                        <x>1047</x>
                        <y>517</y>
                        <z>0</z>
                        <width>448.660614014</width>
                        <height>98.486473083</height>
                        <depth>0</depth>
                        <hotspotX>0.500717342</hotspotX>
                        <hotspotY>0.503268003</hotspotY>
                        <angle>0</angle>
                        <opacity>1</opacity>
                    </world>
                </instance>
                <instance type="text_jawaban" uid="1722">
                    <properties>
                        <text>2/3</text>
                        <initial-visibility>Visible</initial-visibility>
                        <font>BM HANNA,-34.6667,400,0</font>
                        <color>255,255,255</color>
                        <horizontal-alignment>Center</horizontal-alignment>
                        <vertical-alignment>Center</vertical-alignment>
                        <hotspot>Top</hotspot>
                        <wrapping>Word</wrapping>
                        <line-height>0</line-height>
                    </properties>
                    <blend-mode>0</blend-mode>
                    <effect-fallback>0</effect-fallback>
                    <world>
                        <x>1041</x>
                        <y>479</y>
                        <z>0</z>
                        <width>364</width>
                        <height>81</height>
                        <depth>0</depth>
                        <hotspotX>0.5</hotspotX>
                        <hotspotY>0</hotspotY>
                        <angle>0</angle>
                        <opacity>1</opacity>
                    </world>
                </instance>
                <instance type="titleLv2Pecahan" uid="1724">
                    <properties>
                        <initial-visibility>Visible</initial-visibility>
                        <initial-animation>Default</initial-animation>
                        <initial-frame>0</initial-frame>
                        <collisions>Enabled</collisions>
                    </properties>
                    <blend-mode>0</blend-mode>
                    <effect-fallback>0</effect-fallback>
                    <world>
                        <x>196.53565979</x>
                        <y>27.112987518</y>
                        <z>0</z>
                        <width>410.043243408</width>
                        <height>80.201293945</height>
                        <depth>0</depth>
                        <hotspotX>0.500298142</hotspotX>
                        <hotspotY>0.501930475</hotspotY>
                        <angle>0</angle>
                        <opacity>1</opacity>
                    </world>
                </instance>
                <instance type="pecNo5Lv2" uid="1723">
                    <properties>
                        <initial-visibility>Visible</initial-visibility>
                        <initial-animation>Default</initial-animation>
                        <initial-frame>0</initial-frame>
                        <collisions>Enabled</collisions>
                    </properties>
                    <blend-mode>0</blend-mode>
                    <effect-fallback>0</effect-fallback>
                    <world>
                        <x>417</x>
                        <y>378</y>
                        <z>0</z>
                        <width>784.705810547</width>
                        <height>385.42086792</height>
                        <depth>0</depth>
                        <hotspotX>0.5</hotspotX>
                        <hotspotY>0.5</hotspotY>
                        <angle>0</angle>
                        <opacity>1</opacity>
                    </world>
                </instance>
            </instances>
            <effects />
        </layer>
    </layers>
    <nonworld-instances />
    <effects />
</c2layout>
