<?xml version="1.0" encoding="utf-8" ?>
<c2eventsheet>
    <!--All the 'name' attributes are ignored by Construct 2 - they are there for readability only.-->
    <name>Penjelasan PBerat No7 Lv2</name>
    <events>
        <event-block sid="668776178005780">
            <conditions>
                <condition id="3" name="On touched object" sid="132070024324843" type="Touch">
                    <param id="0" name="Object">btnNextSoalLevel2</param>
                </condition>
            </conditions>
            <actions>
                <action id="-2" name="Go to layout" sid="166090132442337" type="System">
                    <param id="0" name="Layout">Kuis PBerat No8 Lv2</param>
                </action>
            </actions>
        </event-block>
    </events>
</c2eventsheet>
